[
    {
        "question": "What courses are offered?",
        "answer": "We offer BCA, BBA, BA, BSc and professional diploma courses."
    },
    {
        "question": "What is the admission process?",
        "answer": "Admissions are based on merit and entrance exams depending on the course."
    },
    {
        "question": "Is hostel facility available?",
        "answer": "Yes, hostel facilities are available for both boys and girls."
    },
    {
        "question": "What is the fee structure?",
        "answer": "Fee structure varies by course. Please contact the accounts department."
    },
    {
        "question": "Does the college provide placements?",
        "answer": "Yes, we have a dedicated placement cell for student recruitment."
    },
    {
        "question": "who made you",
        "answer": "I was created by thakur Raj kumar."
    },
    {
        "question": "who is the hod of bca and bba department?",
        "answer": "Dr.Parul Mahajan is hod of departments."
    },
    {
        "question": "Hello ?",
        "answer": "Hey i am fine and how i can help you."

    }
]